{
  "version": "7",
  "dialect": "postgresql",
  "entries": [
    {
      "idx": 0,
      "version": "7",
      "when": 1745558144425,
      "tag": "0000_cool_thundra",
      "breakpoints": true
    },
    {
      "idx": 1,
      "version": "7",
      "when": 1745559111509,
      "tag": "0001_steady_vivisector",
      "breakpoints": true
    },
    {
      "idx": 2,
      "version": "7",
      "when": 1745567369014,
      "tag": "0002_wide_nocturne",
      "breakpoints": true
    },
    {
      "idx": 3,
      "version": "7",
      "when": 1745597358822,
      "tag": "0003_friendly_gateway",
      "breakpoints": true
    }
  ]
}